py_address_parser
