Metadata-Version: 1.0
Name: py-address-parser
Version: 0.2.1
Summary: An address parsing library for Python based on usaddress.
Home-page: https://github.com/R-Andrei/py_address_parser
Author: Rares Andrei Faragau
Author-email: faragau.rares@gmail.com
License: MIT
Platform: UNKNOWN
